{"assets/ak.png":["assets/ak.png"],"assets/alegria.png":["assets/alegria.png"],"assets/android.png":["assets/android.png"],"assets/bg.jpg":["assets/bg.jpg"],"assets/css.png":["assets/css.png"],"assets/dart.png":["assets/dart.png"],"assets/explore.png":["assets/explore.png"],"assets/firebase.png":["assets/firebase.png"],"assets/flutter.png":["assets/flutter.png"],"assets/git.png":["assets/git.png"],"assets/github.png":["assets/github.png"],"assets/gmail.png":["assets/gmail.png"],"assets/go.png":["assets/go.png"],"assets/gql.png":["assets/gql.png"],"assets/heroku.png":["assets/heroku.png"],"assets/html.png":["assets/html.png"],"assets/js.png":["assets/js.png"],"assets/linkedin.png":["assets/linkedin.png"],"assets/me.png":["assets/me.png"],"assets/mongo.png":["assets/mongo.png"],"assets/node.png":["assets/node.png"],"assets/play.png":["assets/play.png"],"assets/profile.jpg":["assets/profile.jpg"],"assets/react.png":["assets/react.png"],"assets/rest.png":["assets/rest.png"],"assets/simba.jpg":["assets/simba.jpg"],"assets/stack.png":["assets/stack.png"],"assets/study.png":["assets/study.png"],"packages/cupertino_icons/assets/CupertinoIcons.ttf":["packages/cupertino_icons/assets/CupertinoIcons.ttf"]}